README.rst
setup.cfg
setup.py
PyAgg.egg-info/PKG-INFO
PyAgg.egg-info/SOURCES.txt
PyAgg.egg-info/dependency_links.txt
PyAgg.egg-info/top_level.txt
pyagg/__init__.py
pyagg/affine.py
pyagg/bboxhelper.py
pyagg/canvas.py
pyagg/graph.py
pyagg/units.py
pyagg/fontTools/__init__.py
pyagg/fontTools/afmLib.py
pyagg/fontTools/agl.py
pyagg/fontTools/cffLib.py
pyagg/fontTools/inspect.py
pyagg/fontTools/merge.py
pyagg/fontTools/subset.py
pyagg/fontTools/t1Lib.py
pyagg/fontTools/ttx.py
pyagg/fontTools/unicode.py
pyagg/fontTools/encodings/MacRoman.py
pyagg/fontTools/encodings/StandardEncoding.py
pyagg/fontTools/encodings/__init__.py
pyagg/fontTools/misc/__init__.py
pyagg/fontTools/misc/arrayTools.py
pyagg/fontTools/misc/bezierTools.py
pyagg/fontTools/misc/eexec.py
pyagg/fontTools/misc/fixedTools.py
pyagg/fontTools/misc/homeResFile.py
pyagg/fontTools/misc/macCreatorType.py
pyagg/fontTools/misc/psCharStrings.py
pyagg/fontTools/misc/psLib.py
pyagg/fontTools/misc/psOperators.py
pyagg/fontTools/misc/py23.py
pyagg/fontTools/misc/sstruct.py
pyagg/fontTools/misc/textTools.py
pyagg/fontTools/misc/transform.py
pyagg/fontTools/misc/xmlReader.py
pyagg/fontTools/misc/xmlWriter.py
pyagg/fontTools/pens/__init__.py
pyagg/fontTools/pens/basePen.py
pyagg/fontTools/pens/boundsPen.py
pyagg/fontTools/pens/cocoaPen.py
pyagg/fontTools/pens/pointInsidePen.py
pyagg/fontTools/pens/qtPen.py
pyagg/fontTools/pens/reportLabPen.py
pyagg/fontTools/pens/transformPen.py
pyagg/fontTools/ttLib/__init__.py
pyagg/fontTools/ttLib/macUtils.py
pyagg/fontTools/ttLib/sfnt.py
pyagg/fontTools/ttLib/standardGlyphOrder.py
pyagg/fontTools/ttLib/tables/B_A_S_E_.py
pyagg/fontTools/ttLib/tables/BitmapGlyphMetrics.py
pyagg/fontTools/ttLib/tables/C_B_D_T_.py
pyagg/fontTools/ttLib/tables/C_B_L_C_.py
pyagg/fontTools/ttLib/tables/C_F_F_.py
pyagg/fontTools/ttLib/tables/C_O_L_R_.py
pyagg/fontTools/ttLib/tables/C_P_A_L_.py
pyagg/fontTools/ttLib/tables/D_S_I_G_.py
pyagg/fontTools/ttLib/tables/DefaultTable.py
pyagg/fontTools/ttLib/tables/E_B_D_T_.py
pyagg/fontTools/ttLib/tables/E_B_L_C_.py
pyagg/fontTools/ttLib/tables/F_F_T_M_.py
