Metadata-Version: 1.1
Name: PyAgg
Version: 0.1
Summary: Simple user-oriented graphics drawing and image manipulation.
Home-page: http://github.com/karimbahgat/PyAgg
Author: Karim Bahgat
Author-email: karim.bahgat.norway@gmail.com
License: MIT
Keywords: graphics rendering drawing visualization imaging AGG aggdraw
Platform: UNKNOWN
Classifier: License :: OSI Approved
Classifier: Programming Language :: Python
Classifier: Development Status :: 4 - Beta
Classifier: Intended Audience :: Developers
Classifier: Intended Audience :: Science/Research
Classifier: Intended Audience :: End Users/Desktop
Classifier: Topic :: Scientific/Engineering :: Visualization
Classifier: Topic :: Multimedia :: Graphics
Classifier: Topic :: Scientific/Engineering :: GIS
Requires: PIL
